jupyter_analysis_extension/__init__.py
jupyter_analysis_extension/_frontend.py
jupyter_analysis_extension/_version.py
jupyter_analysis_extension/example.py
jupyter_analysis_extension/logger.py
jupyter_analysis_extension/widget_analysis.py
jupyter_analysis_extension/widget_func.py
jupyter_analysis_extension/widget_guide.py
jupyter_analysis_extension/widget_style.py
jupyter_analysis_extension/statistics_operation/__init__.py
jupyter_analysis_extension/statistics_operation/anova_ancova.py
jupyter_analysis_extension/statistics_operation/anova_kruskal.py
jupyter_analysis_extension/statistics_operation/anova_oneway.py
jupyter_analysis_extension/statistics_operation/anova_rm.py
jupyter_analysis_extension/statistics_operation/common_util.py
jupyter_analysis_extension/statistics_operation/frequencies_chi_square.py
jupyter_analysis_extension/statistics_operation/general_linear_regression.py
jupyter_analysis_extension/statistics_operation/logistic_regression.py
jupyter_analysis_extension/statistics_operation/statistic_op.py
jupyter_analysis_extension/statistics_operation/statistic_original.py
jupyter_analysis_extension/statistics_operation/t_test_ind_sample.py
jupyter_analysis_extension/statistics_operation/t_test_one_sample.py
jupyter_analysis_extension/statistics_operation/t_test_pair_sample.py
jupyter_analysis_extension/statistics_operation/anova/__init__.py
jupyter_analysis_extension/statistics_operation/anova/anova_ancova.py
jupyter_analysis_extension/statistics_operation/anova/anova_friedman.py
jupyter_analysis_extension/statistics_operation/anova/anova_kruskal.py
jupyter_analysis_extension/statistics_operation/anova/anova_oneway.py
jupyter_analysis_extension/statistics_operation/anova/anova_rm.py
jupyter_analysis_extension/statistics_operation/basic/__init__.py
jupyter_analysis_extension/statistics_operation/basic/basic_analysis.py
jupyter_analysis_extension/statistics_operation/basic/basic_pca.py
jupyter_analysis_extension-1.1.5.dist-info/LICENSE
jupyter_analysis_extension-1.1.5.dist-info/METADATA
jupyter_analysis_extension-1.1.5.dist-info/WHEEL
jupyter_analysis_extension-1.1.5.dist-info/top_level.txt
jupyter_analysis_extension-1.1.5.dist-info/RECORD
