Metadata-Version: 2.1
Name: jupyter-analysis-extension
Version: 1.1.5
Summary: A Jupyter Extension for Data Analysis
Home-page: https://github.com/KyoungjunPark/ipywidget_statistics
Author: Kyoungjun Park
Author-email: parkkjun525@gmail.com
License: UNKNOWN
Project-URL: Bug Tracker, https://github.com/KyoungjunPark/ipywidget_statistics/issues
Platform: UNKNOWN
Classifier: Programming Language :: Python :: 3
Classifier: License :: OSI Approved :: GNU General Public License v3 or later (GPLv3+)
Classifier: Operating System :: OS Independent
Requires-Python: >=3.6
Requires-Dist: ipykernel (>=5.5.3)
Requires-Dist: ipywidgets (~=7.6.3)
Requires-Dist: ipython (~=7.26.0)
Requires-Dist: traitlets (>=5.0.5)
Requires-Dist: pandas (>=1.2.4)
Requires-Dist: qgrid (~=1.3.1)
Requires-Dist: numpy (>=1.20.2)
Requires-Dist: plotly (>=4.14.3)
Requires-Dist: statsmodels (>=0.12.2)
Requires-Dist: scipy (>=1.6.3)
Requires-Dist: seaborn (>=0.11.1)
Requires-Dist: matplotlib (~=3.4.2)
Requires-Dist: jupyterlab
Requires-Dist: notebook
Requires-Dist: setuptools (~=49.6.0)
Requires-Dist: scikit-learn (~=0.24.2)
Requires-Dist: ipympl
Requires-Dist: ipyevents (~=2.0.1)
Requires-Dist: future (~=0.18.2)
Requires-Dist: nbformat (~=5.1.3)
Requires-Dist: nbconvert
Requires-Dist: pdfkit
Requires-Dist: xhtml2pdf
Requires-Dist: imgkit
Requires-Dist: pingouin
